[
  {
    "id": "member_001",
    "firstName": "Bernhard",
    "lastName": "Drewes",
    "name": "Bernhard Drewes",
    "strasse": "Domeierstr. 19",
    "plz": "37574",
    "ort": "Einbeck",
    "email": "",
    "gender": "male",
    "isActive": true,
    "birthYear": null,
    "mitgliedsnummer": "001",
    "telefon": "",
    "mobil": "",
    "eintrittsdatum": null,
    "alter": 0,
    "clubId": "SGi_Einbeck"
  },
  {
    "id": "member_002",
    "firstName": "Hans-Gert",
    "lastName": "Weseloh",
    "name": "Hans-Gert Weseloh",
    "strasse": "Oleburg 12",
    "plz": "37574",
    "ort": "Einbeck",
    "email": "",
    "gender": "male",
    "isActive": true,
    "birthYear": null,
    "mitgliedsnummer": "002",
    "telefon": "",
    "mobil": "",
    "eintrittsdatum": null,
    "alter": 0,
    "clubId": "SGi_Einbeck"
  },
  {
    "id": "member_003",
    "firstName": "Ingo",
    "lastName": "Müller",
    "name": "Ingo Müller",
    "strasse": "Knochenhauerstr. 32",
    "plz": "37574",
    "ort": "Einbeck",
    "email": "",
    "gender": "male",
    "isActive": true,
    "birthYear": null,
    "mitgliedsnummer": "003",
    "telefon": "",
    "mobil": "",
    "eintrittsdatum": null,
    "alter": 0,
    "clubId": "SGi_Einbeck"
  },
  {
    "id": "member_004",
    "firstName": "Horst",
    "lastName": "Tinnefeld",
    "name": "Horst Tinnefeld",
    "strasse": "Fichtestr. 10",
    "plz": "37574",
    "ort": "Einbeck",
    "email": "",
    "gender": "male",
    "isActive": true,
    "birthYear": null,
    "mitgliedsnummer": "004",
    "telefon": "",
    "mobil": "",
    "eintrittsdatum": null,
    "alter": 0,
    "clubId": "SGi_Einbeck"
  },
  {
    "id": "member_005",
    "firstName": "Eckhard",
    "lastName": "Schmidt",
    "name": "Eckhard Schmidt",
    "strasse": "Beethovenstr. 29",
    "plz": "37574",
    "ort": "Einbeck",
    "email": "",
    "gender": "male",
    "isActive": true,
    "birthYear": null,
    "mitgliedsnummer": "005",
    "telefon": "",
    "mobil": "",
    "eintrittsdatum": null,
    "alter": 0,
    "clubId": "SGi_Einbeck"
  },
  {
    "id": "member_006",
    "firstName": "Uwe",
    "lastName": "Arlt",
    "name": "Uwe Arlt",
    "strasse": "Odagser Hauptstr. 19",
    "plz": "37574",
    "ort": "Einbeck",
    "email": "",
    "gender": "male",
    "isActive": true,
    "birthYear": null,
    "mitgliedsnummer": "006",
    "telefon": "",
    "mobil": "",
    "eintrittsdatum": null,
    "alter": 0,
    "clubId": "SGi_Einbeck"
  },
  {
    "id": "member_007",
    "firstName": "Ursula",
    "lastName": "Grönke",
    "name": "Ursula Grönke",
    "strasse": "Beethovenstr. 1a",
    "plz": "37574",
    "ort": "Einbeck",
    "email": "",
    "gender": "female",
    "isActive": true,
    "birthYear": null,
    "mitgliedsnummer": "007",
    "telefon": "",
    "mobil": "",
    "eintrittsdatum": null,
    "alter": 0,
    "clubId": "SGi_Einbeck"
  },
  {
    "id": "member_008",
    "firstName": "Beate",
    "lastName": "Menzel",
    "name": "Beate Menzel",
    "strasse": "Bundesstr. 38",
    "plz": "37627",
    "ort": "Lenne",
    "email": "menzel@live.de",
    "gender": "female",
    "isActive": true,
    "birthYear": null,
    "mitgliedsnummer": "008",
    "telefon": "",
    "mobil": "",
    "eintrittsdatum": null,
    "alter": 0,
    "clubId": "SGi_Einbeck"
  },
  {
    "id": "member_009",
    "firstName": "Reiner",
    "lastName": "Schoppe",
    "name": "Reiner Schoppe",
    "strasse": "Schützenstr. 38",
    "plz": "37574",
    "ort": "Einbeck",
    "email": "aschoppe@gmx.net",
    "gender": "male",
    "isActive": true,
    "birthYear": null,
    "mitgliedsnummer": "009",
    "telefon": "",
    "mobil": "",
    "eintrittsdatum": null,
    "alter": 0,
    "clubId": "SGi_Einbeck"
  },
  {
    "id": "member_010",
    "firstName": "Elias",
    "lastName": "Michalik",
    "name": "Elias Michalik",
    "strasse": "Offenbachstr. 30",
    "plz": "37574",
    "ort": "Einbeck",
    "email": "elias.michalik@gmx.de",
    "gender": "male",
    "isActive": true,
    "birthYear": null,
    "mitgliedsnummer": "010",
    "telefon": "",
    "mobil": "",
    "eintrittsdatum": null,
    "alter": 0,
    "clubId": "SGi_Einbeck"
  },
  {
    "id": "member_011",
    "firstName": "Paul",
    "lastName": "Borodycz",
    "name": "Paul Borodycz",
    "strasse": "Holiger Weg 12",
    "plz": "37574",
    "ort": "Einbeck – Wenzen",
    "email": "esmiralda@live.de",
    "gender": "male",
    "isActive": true,
    "birthYear": null,
    "mitgliedsnummer": "011",
    "telefon": "",
    "mobil": "",
    "eintrittsdatum": null,
    "alter": 0,
    "clubId": "SGi_Einbeck"
  },
  {
    "id": "member_012",
    "firstName": "Frank",
    "lastName": "Rosenthal",
    "name": "Frank Rosenthal",
    "strasse": "Gänselandweg 5",
    "plz": "37574",
    "ort": "Einbeck",
    "email": "fr1410@web.de",
    "gender": "male",
    "isActive": true,
    "birthYear": null,
    "mitgliedsnummer": "012",
    "telefon": "",
    "mobil": "",
    "eintrittsdatum": null,
    "alter": 0,
    "clubId": "SGi_Einbeck"
  },
  {
    "id": "member_013",
    "firstName": "Friedel",
    "lastName": "Schimpf",
    "name": "Friedel Schimpf",
    "strasse": "Hansestr. 1",
    "plz": "37574",
    "ort": "Einbeck",
    "email": "frie_schi@t-online.de",
    "gender": "male",
    "isActive": true,
    "birthYear": null,
    "mitgliedsnummer": "013",
    "telefon": "",
    "mobil": "",
    "eintrittsdatum": null,
    "alter": 0,
    "clubId": "SGi_Einbeck"
  },
  {
    "id": "member_014",
    "firstName": "Helmut",
    "lastName": "Meyer",
    "name": "Helmut Meyer",
    "strasse": "Waldstr. 16",
    "plz": "37574",
    "ort": "Einbeck",
    "email": "helmutmeyer.einbeck@web.de",
    "gender": "male",
    "isActive": true,
    "birthYear": null,
    "mitgliedsnummer": "014",
    "telefon": "",
    "mobil": "",
    "eintrittsdatum": null,
    "alter": 0,
    "clubId": "SGi_Einbeck"
  },
  {
    "id": "member_015",
    "firstName": "Inge",
    "lastName": "Kriegsmann",
    "name": "Inge Kriegsmann",
    "strasse": "Grimsehlstr. 5",
    "plz": "37574",
    "ort": "Einbeck",
    "email": "inge@kriegsmann-consulting.de",
    "gender": "female",
    "isActive": true,
    "birthYear": null,
    "mitgliedsnummer": "015",
    "telefon": "",
    "mobil": "",
    "eintrittsdatum": null,
    "alter": 0,
    "clubId": "SGi_Einbeck"
  },
  {
    "id": "member_016",
    "firstName": "Monika",
    "lastName": "Lachstädter",
    "name": "Monika Lachstädter",
    "strasse": "Einbecker Weg 5",
    "plz": "37586",
    "ort": "Dassel-Hilwartshausen",
    "email": "j.lachstaedter@t-online.de",
    "gender": "female",
    "isActive": true,
    "birthYear": null,
    "mitgliedsnummer": "016",
    "telefon": "",
    "mobil": "",
    "eintrittsdatum": null,
    "alter": 0,
    "clubId": "SGi_Einbeck"
  },
  {
    "id": "member_017",
    "firstName": "Jens",
    "lastName": "Lachstädter",
    "name": "Jens Lachstädter",
    "strasse": "Einbecker Weg 5",
    "plz": "37586",
    "ort": "Dassel-Hilwartshausen",
    "email": "j.lachstaedter@t-online.de",
    "gender": "male",
    "isActive": true,
    "birthYear": null,
    "mitgliedsnummer": "017",
    "telefon": "",
    "mobil": "",
    "eintrittsdatum": null,
    "alter": 0,
    "clubId": "SGi_Einbeck"
  },
  {
    "id": "member_018",
    "firstName": "Erik",
    "lastName": "Lachstädter",
    "name": "Erik Lachstädter",
    "strasse": "Einbecker Weg 5",
    "plz": "37586",
    "ort": "Dassel-Hilwartshausen",
    "email": "j.lachstaedter@t-online.de",
    "gender": "male",
    "isActive": true,
    "birthYear": null,
    "mitgliedsnummer": "018",
    "telefon": "",
    "mobil": "",
    "eintrittsdatum": null,
    "alter": 0,
    "clubId": "SGi_Einbeck"
  },
  {
    "id": "member_019",
    "firstName": "Patrick",
    "lastName": "Jaeger",
    "name": "Patrick Jaeger",
    "strasse": "Hannover",
    "plz": "",
    "ort": "jaeger_patrik@web.de",
    "email": "",
    "gender": "male",
    "isActive": true,
    "birthYear": null,
    "mitgliedsnummer": "019",
    "telefon": "",
    "mobil": "",
    "eintrittsdatum": null,
    "alter": 0,
    "clubId": "SGi_Einbeck"
  },
  {
    "id": "member_020",
    "firstName": "Julien",
    "lastName": "Bünger",
    "name": "Julien Bünger",
    "strasse": "Beethovenstraße 20",
    "plz": "37574",
    "ort": "Einbeck",
    "email": "Julien1194@web.de",
    "gender": "male",
    "isActive": true,
    "birthYear": null,
    "mitgliedsnummer": "020",
    "telefon": "",
    "mobil": "",
    "eintrittsdatum": null,
    "alter": 0,
    "clubId": "SGi_Einbeck"
  },
  {
    "id": "member_021",
    "firstName": "Karl-Arthur",
    "lastName": "Aurin",
    "name": "Karl-Arthur Aurin",
    "strasse": "Unbekannt",
    "plz": "37574",
    "ort": "Einbeck - Greene",
    "email": "karl-arthur.aurin@outlook.de",
    "gender": "male",
    "isActive": true,
    "birthYear": null,
    "mitgliedsnummer": "021",
    "telefon": "",
    "mobil": "",
    "eintrittsdatum": null,
    "alter": 0,
    "clubId": "SGi_Einbeck"
  },
  {
    "id": "member_022",
    "firstName": "Kerstin",
    "lastName": "Hundertmark",
    "name": "Kerstin Hundertmark",
    "strasse": "Reinserturmweg 5",
    "plz": "37574",
    "ort": "Einbeck",
    "email": "kerstin.hundertmark@gmx.de",
    "gender": "female",
    "isActive": true,
    "birthYear": null,
    "mitgliedsnummer": "022",
    "telefon": "",
    "mobil": "",
    "eintrittsdatum": null,
    "alter": 0,
    "clubId": "SGi_Einbeck"
  },
  {
    "id": "member_023",
    "firstName": "Karsten",
    "lastName": "Reinert",
    "name": "Karsten Reinert",
    "strasse": "Reinserturmweg 5",
    "plz": "37574",
    "ort": "Einbeck",
    "email": "",
    "gender": "male",
    "isActive": true,
    "birthYear": null,
    "mitgliedsnummer": "023",
    "telefon": "",
    "mobil": "",
    "eintrittsdatum": null,
    "alter": 0,
    "clubId": "SGi_Einbeck"
  },
  {
    "id": "member_024",
    "firstName": "Klaus",
    "lastName": "Klapproth",
    "name": "Klaus Klapproth",
    "strasse": "Neddenstr. 4",
    "plz": "37574",
    "ort": "Einbeck",
    "email": "Klaus.Klapproth@gmx.de",
    "gender": "male",
    "isActive": true,
    "birthYear": null,
    "mitgliedsnummer": "024",
    "telefon": "",
    "mobil": "",
    "eintrittsdatum": null,
    "alter": 0,
    "clubId": "SGi_Einbeck"
  },
  {
    "id": "member_025",
    "firstName": "Alexander",
    "lastName": "Kloss",
    "name": "Alexander Kloss",
    "strasse": "Negenborner Weg 58",
    "plz": "37574",
    "ort": "Einbeck",
    "email": "klossalexander@aol.com",
    "gender": "male",
    "isActive": true,
    "birthYear": null,
    "mitgliedsnummer": "025",
    "telefon": "",
    "mobil": "",
    "eintrittsdatum": null,
    "alter": 0,
    "clubId": "SGi_Einbeck"
  },
  {
    "id": "member_026",
    "firstName": "Martin",
    "lastName": "Baselt",
    "name": "Martin Baselt",
    "strasse": "Sonnenblick 10",
    "plz": "37632",
    "ort": "Eimen",
    "email": "ksve@baselt.de",
    "gender": "male",
    "isActive": true,
    "birthYear": null,
    "mitgliedsnummer": "026",
    "telefon": "",
    "mobil": "",
    "eintrittsdatum": null,
    "alter": 0,
    "clubId": "SGi_Einbeck"
  },
  {
    "id": "member_027",
    "firstName": "Leon",
    "lastName": "Loresch",
    "name": "Leon Loresch",
    "strasse": "Am Wasserbruch 7",
    "plz": "37574",
    "ort": "Einbeck",
    "email": "leonloresch@gmail.com",
    "gender": "male",
    "isActive": true,
    "birthYear": null,
    "mitgliedsnummer": "027",
    "telefon": "",
    "mobil": "",
    "eintrittsdatum": null,
    "alter": 0,
    "clubId": "SGi_Einbeck"
  },
  {
    "id": "member_028",
    "firstName": "Lisa",
    "lastName": "Russinow",
    "name": "Lisa Russinow",
    "strasse": "Lessingstr. 23",
    "plz": "37574",
    "ort": "Einbeck",
    "email": "lisarussinow@mail.ru",
    "gender": "female",
    "isActive": true,
    "birthYear": null,
    "mitgliedsnummer": "028",
    "telefon": "",
    "mobil": "",
    "eintrittsdatum": null,
    "alter": 0,
    "clubId": "SGi_Einbeck"
  },
  {
    "id": "member_029",
    "firstName": "Lucia",
    "lastName": "Hentschel",
    "name": "Lucia Hentschel",
    "strasse": "Teichenweg 1B",
    "plz": "37574",
    "ort": "Einbeck",
    "email": "lucia.hentschel@alice.de",
    "gender": "female",
    "isActive": true,
    "birthYear": null,
    "mitgliedsnummer": "029",
    "telefon": "",
    "mobil": "",
    "eintrittsdatum": null,
    "alter": 0,
    "clubId": "SGi_Einbeck"
  },
  {
    "id": "member_030",
    "firstName": "Wilfried",
    "lastName": "Hentschel",
    "name": "Wilfried Hentschel",
    "strasse": "Teichenweg 1B",
    "plz": "37574",
    "ort": "Einbeck",
    "email": "",
    "gender": "male",
    "isActive": true,
    "birthYear": null,
    "mitgliedsnummer": "030",
    "telefon": "",
    "mobil": "",
    "eintrittsdatum": null,
    "alter": 0,
    "clubId": "SGi_Einbeck"
  },
  {
    "id": "member_031",
    "firstName": "Stephanie",
    "lastName": "Bünger",
    "name": "Stephanie Bünger",
    "strasse": "Luisenstr. 10",
    "plz": "37574",
    "ort": "Einbeck",
    "email": "",
    "gender": "female",
    "isActive": true,
    "birthYear": null,
    "mitgliedsnummer": "031",
    "telefon": "",
    "mobil": "",
    "eintrittsdatum": null,
    "alter": 0,
    "clubId": "SGi_Einbeck"
  },
  {
    "id": "member_032",
    "firstName": "Marcel",
    "lastName": "Bünger",
    "name": "Marcel Bünger",
    "strasse": "Luisenstr. 10",
    "plz": "37574",
    "ort": "Einbeck",
    "email": "marcel.buenger@gmx.de",
    "gender": "male",
    "isActive": true,
    "birthYear": null,
    "mitgliedsnummer": "032",
    "telefon": "",
    "mobil": "",
    "eintrittsdatum": null,
    "alter": 0,
    "clubId": "SGi_Einbeck"
  },
  {
    "id": "member_033",
    "firstName": "Nikita",
    "lastName": "Dykun",
    "name": "Nikita Dykun",
    "strasse": "Breil 6",
    "plz": "37574",
    "ort": "Einbeck",
    "email": "marina_design_@ukr.net",
    "gender": "male",
    "isActive": true,
    "birthYear": null,
    "mitgliedsnummer": "033",
    "telefon": "",
    "mobil": "",
    "eintrittsdatum": null,
    "alter": 0,
    "clubId": "SGi_Einbeck"
  },
  {
    "id": "member_034",
    "firstName": "Monika",
    "lastName": "Witte",
    "name": "Monika Witte",
    "strasse": "Am Klee 4",
    "plz": "37574",
    "ort": "Einbeck",
    "email": "mw290650@aol.com",
    "gender": "female",
    "isActive": true,
    "birthYear": null,
    "mitgliedsnummer": "034",
    "telefon": "",
    "mobil": "",
    "eintrittsdatum": null,
    "alter": 0,
    "clubId": "SGi_Einbeck"
  },
  {
    "id": "member_035",
    "firstName": "Nathalie",
    "lastName": "Buchhage",
    "name": "Nathalie Buchhage",
    "strasse": "Teichenweg 1",
    "plz": "37574",
    "ort": "Einbeck",
    "email": "nathalie.buchhage@gmail.com",
    "gender": "female",
    "isActive": true,
    "birthYear": null,
    "mitgliedsnummer": "035",
    "telefon": "",
    "mobil": "",
    "eintrittsdatum": null,
    "alter": 0,
    "clubId": "SGi_Einbeck"
  },
  {
    "id": "member_036",
    "firstName": "Sven",
    "lastName": "Buchhage",
    "name": "Sven Buchhage",
    "strasse": "Teichenweg 1",
    "plz": "37574",
    "ort": "Einbeck",
    "email": "",
    "gender": "male",
    "isActive": true,
    "birthYear": null,
    "mitgliedsnummer": "036",
    "telefon": "",
    "mobil": "",
    "eintrittsdatum": null,
    "alter": 0,
    "clubId": "SGi_Einbeck"
  },
  {
    "id": "member_040",
    "firstName": "Reiner",
    "lastName": "Goebel",
    "name": "Reiner Goebel",
    "strasse": "Gleiwitzer Str. 6",
    "plz": "37574",
    "ort": "Einbeck",
    "email": "reiner.goebel@t-online.de",
    "gender": "male",
    "isActive": true,
    "birthYear": null,
    "mitgliedsnummer": "040",
    "telefon": "",
    "mobil": "",
    "eintrittsdatum": null,
    "alter": 0,
    "clubId": "SGi_Einbeck"
  },
  {
    "id": "member_041",
    "firstName": "Kerstin",
    "lastName": "Guttmann",
    "name": "Kerstin Guttmann",
    "strasse": "Hainsteinhof 14",
    "plz": "37079",
    "ort": "Göttingen",
    "email": "rk.guttmann@web.de",
    "gender": "female",
    "isActive": true,
    "birthYear": null,
    "mitgliedsnummer": "041",
    "telefon": "",
    "mobil": "",
    "eintrittsdatum": null,
    "alter": 0,
    "clubId": "SGi_Einbeck"
  },
  {
    "id": "member_042",
    "firstName": "Olivia",
    "lastName": "Mau",
    "name": "Olivia Mau",
    "strasse": "Negenborner Weg 114",
    "plz": "37574",
    "ort": "Einbeck",
    "email": "",
    "gender": "female",
    "isActive": true,
    "birthYear": null,
    "mitgliedsnummer": "042",
    "telefon": "",
    "mobil": "",
    "eintrittsdatum": null,
    "alter": 0,
    "clubId": "SGi_Einbeck"
  },
  {
    "id": "member_043",
    "firstName": "Sara",
    "lastName": "Mau",
    "name": "Sara Mau",
    "strasse": "Negenborner Weg 114",
    "plz": "37574",
    "ort": "Einbeck",
    "email": "",
    "gender": "female",
    "isActive": true,
    "birthYear": null,
    "mitgliedsnummer": "043",
    "telefon": "",
    "mobil": "",
    "eintrittsdatum": null,
    "alter": 0,
    "clubId": "SGi_Einbeck"
  },
  {
    "id": "member_044",
    "firstName": "Julius",
    "lastName": "Mau",
    "name": "Julius Mau",
    "strasse": "Negenborner Weg 114",
    "plz": "37574",
    "ort": "Einbeck",
    "email": "",
    "gender": "male",
    "isActive": true,
    "birthYear": null,
    "mitgliedsnummer": "044",
    "telefon": "",
    "mobil": "",
    "eintrittsdatum": null,
    "alter": 0,
    "clubId": "SGi_Einbeck"
  },
  {
    "id": "member_045",
    "firstName": "Sigrid",
    "lastName": "Wulff",
    "name": "Sigrid Wulff",
    "strasse": "Schützenstr. 19",
    "plz": "37574",
    "ort": "Einbeck",
    "email": "schrader-sigrid@t-online.de",
    "gender": "female",
    "isActive": true,
    "birthYear": null,
    "mitgliedsnummer": "045",
    "telefon": "",
    "mobil": "",
    "eintrittsdatum": null,
    "alter": 0,
    "clubId": "SGi_Einbeck"
  },
  {
    "id": "member_046",
    "firstName": "Harald",
    "lastName": "Wulff",
    "name": "Harald Wulff",
    "strasse": "Schützenstr. 19",
    "plz": "37574",
    "ort": "Einbeck",
    "email": "",
    "gender": "male",
    "isActive": true,
    "birthYear": null,
    "mitgliedsnummer": "046",
    "telefon": "",
    "mobil": "",
    "eintrittsdatum": null,
    "alter": 0,
    "clubId": "SGi_Einbeck"
  },
  {
    "id": "member_047",
    "firstName": "Thomas",
    "lastName": "Jaeger",
    "name": "Thomas Jaeger",
    "strasse": "Grimsehlstr. 5",
    "plz": "37574",
    "ort": "Einbeck",
    "email": "thomas.jaeger.64@gmx.de",
    "gender": "male",
    "isActive": true,
    "birthYear": null,
    "mitgliedsnummer": "047",
    "telefon": "",
    "mobil": "",
    "eintrittsdatum": null,
    "alter": 0,
    "clubId": "SGi_Einbeck"
  },
  {
    "id": "member_048",
    "firstName": "Ulrike",
    "lastName": "Jaeger",
    "name": "Ulrike Jaeger",
    "strasse": "37574 Einbeck",
    "plz": "",
    "ort": "u.jaeger910@gmail.com",
    "email": "",
    "gender": "female",
    "isActive": true,
    "birthYear": null,
    "mitgliedsnummer": "048",
    "telefon": "",
    "mobil": "",
    "eintrittsdatum": null,
    "alter": 0,
    "clubId": "SGi_Einbeck"
  },
  {
    "id": "member_049",
    "firstName": "Stefan",
    "lastName": "Beumer",
    "name": "Stefan Beumer",
    "strasse": "Marktplatz 16 - 18",
    "plz": "37574",
    "ort": "Einbeck",
    "email": "vorstandssekretariat@sparkasse-einbeck.de",
    "gender": "male",
    "isActive": true,
    "birthYear": null,
    "mitgliedsnummer": "049",
    "telefon": "",
    "mobil": "",
    "eintrittsdatum": null,
    "alter": 0,
    "clubId": "SGi_Einbeck"
  },
  {
    "id": "member_050",
    "firstName": "Annika",
    "lastName": "Schoppe",
    "name": "Annika Schoppe",
    "strasse": "Schützenstr. 38",
    "plz": "37574",
    "ort": "Einbeck",
    "email": "Aschoppe@arcor.de",
    "gender": "female",
    "isActive": true,
    "birthYear": null,
    "mitgliedsnummer": "050",
    "telefon": "",
    "mobil": "",
    "eintrittsdatum": null,
    "alter": 0,
    "clubId": "SGi_Einbeck"
  },
  {
    "id": "member_051",
    "firstName": "Ludwig",
    "lastName": "Wiesemüller",
    "name": "Ludwig Wiesemüller",
    "strasse": "Königsberger Stieg 7",
    "plz": "37574",
    "ort": "Einbeck - Billerbeck",
    "email": "wiesemueller300@gmail.com",
    "gender": "male",
    "isActive": true,
    "birthYear": null,
    "mitgliedsnummer": "051",
    "telefon": "",
    "mobil": "",
    "eintrittsdatum": null,
    "alter": 0,
    "clubId": "SGi_Einbeck"
  },
  {
    "id": "member_052",
    "firstName": "Dirk",
    "lastName": "Heinemeyer",
    "name": "Dirk Heinemeyer",
    "strasse": "Stuckenbreite 5a",
    "plz": "37574",
    "ort": "Einbeck - Avendshausen",
    "email": "dheinemeyer75@gmail.com",
    "gender": "male",
    "isActive": true,
    "birthYear": null,
    "mitgliedsnummer": "052",
    "telefon": "",
    "mobil": "",
    "eintrittsdatum": null,
    "alter": 0,
    "clubId": "SGi_Einbeck"
  },
  {
    "id": "member_053",
    "firstName": "Daniela",
    "lastName": "Coors",
    "name": "Daniela Coors",
    "strasse": "Bismarckstr. 4a",
    "plz": "37574",
    "ort": "Einbeck",
    "email": "",
    "gender": "female",
    "isActive": true,
    "birthYear": null,
    "mitgliedsnummer": "053",
    "telefon": "",
    "mobil": "",
    "eintrittsdatum": null,
    "alter": 0,
    "clubId": "SGi_Einbeck"
  },
  {
    "id": "member_054",
    "firstName": "Marcel",
    "lastName": "Leiding",
    "name": "Marcel Leiding",
    "strasse": "Bismarckstr. 4a",
    "plz": "37574",
    "ort": "Einbeck",
    "email": "",
    "gender": "male",
    "isActive": true,
    "birthYear": null,
    "mitgliedsnummer": "054",
    "telefon": "",
    "mobil": "",
    "eintrittsdatum": null,
    "alter": 0,
    "clubId": "SGi_Einbeck"
  },
  {
    "id": "member_055",
    "firstName": "Martina",
    "lastName": "Reinert",
    "name": "Martina Reinert",
    "strasse": "Hagebuttenstr. 9",
    "plz": "37574",
    "ort": "Einbeck",
    "email": "",
    "gender": "female",
    "isActive": true,
    "birthYear": null,
    "mitgliedsnummer": "055",
    "telefon": "",
    "mobil": "",
    "eintrittsdatum": null,
    "alter": 0,
    "clubId": "SGi_Einbeck"
  },
  {
    "id": "member_056",
    "firstName": "Hans-Jürgen",
    "lastName": "Reinert",
    "name": "Hans-Jürgen Reinert",
    "strasse": "Hagebuttenstr. 9",
    "plz": "37574",
    "ort": "Einbeck",
    "email": "",
    "gender": "male",
    "isActive": true,
    "birthYear": null,
    "mitgliedsnummer": "056",
    "telefon": "",
    "mobil": "",
    "eintrittsdatum": null,
    "alter": 0,
    "clubId": "SGi_Einbeck"
  },
  {
    "id": "member_057",
    "firstName": "Regine",
    "lastName": "Reinert",
    "name": "Regine Reinert",
    "strasse": "Reinserturmweg 5",
    "plz": "37574",
    "ort": "Einbeck",
    "email": "",
    "gender": "female",
    "isActive": true,
    "birthYear": null,
    "mitgliedsnummer": "057",
    "telefon": "",
    "mobil": "",
    "eintrittsdatum": null,
    "alter": 0,
    "clubId": "SGi_Einbeck"
  },
  {
    "id": "member_058",
    "firstName": "Andrej",
    "lastName": "Sawtschenko",
    "name": "Andrej Sawtschenko",
    "strasse": "Albert-Einstein-Straße 7",
    "plz": "37574",
    "ort": "Einbeck",
    "email": "",
    "gender": "male",
    "isActive": true,
    "birthYear": null,
    "mitgliedsnummer": "058",
    "telefon": "",
    "mobil": "",
    "eintrittsdatum": null,
    "alter": 0,
    "clubId": "SGi_Einbeck"
  },
  {
    "id": "member_059",
    "firstName": "Antonia",
    "lastName": "Weber",
    "name": "Antonia Weber",
    "strasse": "Neddenstr. 28",
    "plz": "37574",
    "ort": "Einbeck",
    "email": "W",
    "gender": "female",
    "isActive": true,
    "birthYear": null,
    "mitgliedsnummer": "059",
    "telefon": "",
    "mobil": "",
    "eintrittsdatum": null,
    "alter": 0,
    "clubId": "SGi_Einbeck"
  },
  {
    "id": "member_060",
    "firstName": "Carolin",
    "lastName": "Weber",
    "name": "Carolin Weber",
    "strasse": "Neddenstr. 28",
    "plz": "37574",
    "ort": "Einbeck",
    "email": "",
    "gender": "female",
    "isActive": true,
    "birthYear": null,
    "mitgliedsnummer": "060",
    "telefon": "",
    "mobil": "",
    "eintrittsdatum": null,
    "alter": 0,
    "clubId": "SGi_Einbeck"
  },
  {
    "id": "member_061",
    "firstName": "Cecile",
    "lastName": "Aylin Dogan",
    "name": "Cecile Aylin Dogan",
    "strasse": "Mühlenbergstr. 31",
    "plz": "37574",
    "ort": "Einbeck",
    "email": "",
    "gender": "female",
    "isActive": true,
    "birthYear": null,
    "mitgliedsnummer": "061",
    "telefon": "",
    "mobil": "",
    "eintrittsdatum": null,
    "alter": 0,
    "clubId": "SGi_Einbeck"
  },
  {
    "id": "member_062",
    "firstName": "Ronja",
    "lastName": "Raue",
    "name": "Ronja Raue",
    "strasse": "Kantor-Hase-Weg 5",
    "plz": "37574",
    "ort": "Einbeck",
    "email": "",
    "gender": "female",
    "isActive": true,
    "birthYear": null,
    "mitgliedsnummer": "062",
    "telefon": "",
    "mobil": "",
    "eintrittsdatum": null,
    "alter": 0,
    "clubId": "SGi_Einbeck"
  },
  {
    "id": "member_063",
    "firstName": "Ingrid",
    "lastName": "Drechsel",
    "name": "Ingrid Drechsel",
    "strasse": "Einbecker Weg 5",
    "plz": "37586",
    "ort": "Dassel-Hilwartshausen",
    "email": "",
    "gender": "female",
    "isActive": true,
    "birthYear": null,
    "mitgliedsnummer": "063",
    "telefon": "",
    "mobil": "",
    "eintrittsdatum": null,
    "alter": 0,
    "clubId": "SGi_Einbeck"
  }
]